exp_orchestrator/metaexperiment_builder.py
exp_orchestrator/test_exp_generation.py
exp_orchestrator/user_utils.py
exp_orchestrator-0.1.0.dist-info/METADATA
exp_orchestrator-0.1.0.dist-info/WHEEL
exp_orchestrator-0.1.0.dist-info/RECORD
