Metadata-Version: 2.1
Name: exp-orchestrator
Version: 0.1.0
Summary: automatically manage and launch complex experiments from slurm (focused on ML workflows)
License: MIT
Author: nightingal3
Requires-Python: >=3.9,<4.0
Classifier: License :: OSI Approved :: MIT License
Classifier: Programming Language :: Python :: 3
Classifier: Programming Language :: Python :: 3.9
Classifier: Programming Language :: Python :: 3.10
Classifier: Programming Language :: Python :: 3.11
Classifier: Programming Language :: Python :: 3.12
Requires-Dist: numpy (>=1.26.4,<2.0.0)
Requires-Dist: pandas (>=2.2.2,<3.0.0)
Requires-Dist: pytest (>=8.1.1,<9.0.0)
Requires-Dist: pyyaml (>=6.0.1,<7.0.0)
